llm_json/json.py
llm_json-0.1.5.dist-info/LICENSE
llm_json-0.1.5.dist-info/METADATA
llm_json-0.1.5.dist-info/WHEEL
llm_json-0.1.5.dist-info/top_level.txt
llm_json-0.1.5.dist-info/RECORD
