Metadata-Version: 2.2
Name: llm-json
Version: 0.1.5
Summary: A JSON library wrapper that gracefully handles markdown-wrapped JSON from LLMs.
Author-email: Alex Volkov <alex@alexw.me>
License: MIT License Copyright (c) 2025 Alex Volkov
Project-URL: Homepage, https://github.com/altryne/llm-json
Keywords: json,LLMs,markdown,ai
Classifier: Programming Language :: Python :: 3
Classifier: Operating System :: OS Independent
Requires-Python: >=3.6
License-File: LICENSE
Provides-Extra: dev
Requires-Dist: pytest>=7.0; extra == "dev"
